Muse_Analysis_Tools-1.1.27.data/data/icons/ABCS.ico
Muse_Analysis_Tools-1.1.27.data/data/resources/resources_rc.py
Muse_Analysis_Tools-1.1.27.data/scripts/analyze_muse_data.py
analyze_muse/ABCS_version.py
analyze_muse/__init__.py
analyze_muse/analyze_muse_data.py
analyze_muse/resources/ABCS.ico
analyze_muse/resources/__init__.py
analyze_muse/resources/resources_rc.py
Muse_Analysis_Tools-1.1.27.dist-info/LICENSE.md
Muse_Analysis_Tools-1.1.27.dist-info/METADATA
Muse_Analysis_Tools-1.1.27.dist-info/WHEEL
Muse_Analysis_Tools-1.1.27.dist-info/top_level.txt
Muse_Analysis_Tools-1.1.27.dist-info/zip-safe
Muse_Analysis_Tools-1.1.27.dist-info/RECORD
