Metadata-Version: 2.1
Name: Muse-Analysis-Tools
Version: 1.1.27
Summary: This package contains code for graphing Muse EEG data
Home-page: https://github.com/digital-cinema-arts/Muse-Analysis-Tools/
Author: debra_peri
Author-email: debragraceperi@gmail.com
License: UNKNOWN
Project-URL: Bug Tracker, https://github.com/digital-cinema-arts/Muse-Analysis-Tools/issues
Project-URL: Documentation, https://github.com/digital-cinema-arts/Muse-Analysis-Tools/wiki
Project-URL: Source Code, https://github.com/digital-cinema-arts/Muse-Analysis-Tools
Keywords: Muse EEG
Platform: UNKNOWN
Classifier: Programming Language :: Python :: 3
Classifier: Operating System :: OS Independent
Classifier: Development Status :: 5 - Production/Stable
Classifier: Topic :: Utilities
Requires: time
Requires: datetime
Requires: numpy
Requires: scipy
Requires: pandas
Requires: math
Requires: h5py
Requires: tables
Requires: bitstring
Requires: os
Requires: sys
Requires: csv
Requires: argparse
Requires: progress
Requires: filetype
Requires: json
Requires: pathlib
Requires: pandas.plotting
Requires: matplotlib
Requires: PyQt5
Requires-Python: >=3.6
Requires-Dist: docutils (>=0.3)
